Workbook

Sheet Create from selection
A1: Month | B1: Sales | C1: Profit
A2: Jan | B2: 10000 | C2: 2500
A3: Feb | B3: 12000 | C3: 3000
A4: Mar | B4: 9000 | C4: 1800
A5: Apr | B5: 15000 | C5: 4000
A9: Product A | B9: 50 | C9: 60 | D9: 70
A10: Product B | B10: 40 | C10: 55 | D10: 65
A11: Product C | B11: 80 | C11: 75 | D11: 90

Sheet DateFunctions
A1: Emp ID | B1: Employee | C1: Joining Date | D1: Delivery Date | E1: Birth Date | F1: Description | G1: Formula | H1: Expected Output (Example) | J1: Explanation of Each Function
A2: 101 | B2: Amit | C2: 45306 | D2: 46225 | E2: 35925 | F2: Returns current date | G2: =TODAY() -> 46297 | H2: 46227
A3: 102 | B3: Neha | C3: 44985 | D3: 46233 | E3: 36482 | F3: Returns current date & time | G3: =NOW() -> 46297.726 | H3: 46227.948 | J3: Function | K3: Purpose | L3: Example
A4: 103 | B4: Rahul | C4: 45721 | D4: 46244 | E4: 35789 | F4: Extracts day | G4: =DAY(TODAY()) -> 2 | H4: 15 | J4: TODAY() | K4: Returns the current system date. | L4: =TODAY() -> 46297
A5: 104 | B5: Priya | C5: 44668 | D5: 46270 | E5: 35103 | F5: Extracts month number | G5: =MONTH(TODAY()) -> 10 | H5: 1 | J5: NOW() | K5: Returns the current date and time. | L5: =NOW() -> 46297.726
A6: 105 | B6: Karan | C6: 44376 | D6: 46310 | E6: 34925 | F6: Extracts year | G6: =YEAR(TODAY()) -> 2026 | H6: 2024 | J6: DATE(year,month,day) | K6: Creates a valid Excel date. | L6: =DATE(2026,12,25) -> 46381
A7: 106 | B7: Sneha | C7: 44022 | D7: 46327 | E7: 35876 | F7: Weekday number | G7: =WEEKDAY(TODAY()) -> 6 | H7: 2 | J7: DAY(date) | K7: Returns the day (1–31). | L7: =DAY(C2) -> 15
A8: 107 | B8: Mohit | C8: 45150 | D8: 46376 | E8: 34335 | F8: Week number | G8: =WEEKNUM(TODAY()) -> 40 | H8: 3 | J8: MONTH(date) | K8: Returns the month (1–12). | L8: =MONTH(C2) -> 1
A9: 108 | B9: Pooja | C9: 44825 | D9: 46402 | E9: 34272 | F9: Month name | G9: =TEXT(TODAY(),"mmmm") -> October | H9: January | J9: YEAR(date) | K9: Returns the year. | L9: =YEAR(C2) -> 2024
A10: 109 | B10: Riya | C10: 45567 | D10: 46443 | E10: 35597 | F10: Day name | G10: =TEXT(TODAY(),"dddd") -> Friday | H10: Monday | J10: WEEKDAY(date) | K10: Returns the day number of the week. | L10: =WEEKDAY(C2) -> 2
A11: 110 | B11: Arjun | C11: 45248 | D11: 46489 | E11: 36262 | F11: Creates a date | H11: 46381 | J11: WEEKNUM(date) | K11: Returns the week number in the year. | L11: =WEEKNUM(C2) -> 3
A12: 111 | B12: Aisha | C12: 44920 | D12: 46537 | E12: 36047 | F12: End of month | H12: 45322 | J12: TEXT(date,"dddd") | K12: Displays the full day name. | L12: Monday
A13: 112 | B13: Vivek | C13: 45662 | D13: 46553 | E13: 35273 | F13: Last day after 2 months | H13: 45382 | J13: TEXT(date,"mmmm") | K13: Displays the full month name. | L13: January
A14: 113 | B14: Simran | C14: 45338 | D14: 46596 | E14: 34710 | F14: Difference in days | H14: 919 (example) | J14: EDATE(date,months) | K14: Adds or subtracts months from a date. | L14: =EDATE(C2,6) -> 45488
A15: 114 | B15: Nitin | C15: 44327 | D15: 46608 | E15: 33881 | F15: Working days | G15: =NETWORKDAYS(C15,D15,5) -> 1630 | H15: Working days count | J15: EOMONTH(date,months) | K15: Returns the last day of the month after a specified number of months. | L15: =EOMONTH(C2,2) -> 45382
A16: 115 | B16: Kavya | C16: 45116 | D16: 46645 | E16: 35932 | F16: Add 30 working days | H16: Date after 30 workdays | J16: DATEDIF(start,end,"Y") | K16: Returns complete years between two dates. | L16: Age calculation
A17: 116 | B17: Deepak | C17: 44787 | D17: 46680 | E17: 34019 | F17: Add 6 months | H17: 45488 | J17: DATEDIF(start,end,"YM") | K17: Returns remaining months after complete years. | L17: Age in months
A18: 117 | B18: Meera | C18: 45536 | D18: 46696 | E18: 35548 | F18: Age in years | H18: Age | J18: DATEDIF(start,end,"MD") | K18: Returns remaining days after complete months. | L18: Age in days
A19: 118 | B19: Sagar | C19: 44114 | D19: 46736 | E19: 35048 | F19: Years & Months | H19: Remaining months | J19: NETWORKDAYS(start,end) | K19: Counts working days (Mon–Fri). | L19: Project duration
A20: 119 | B20: Anjali | C20: 45242 | D20: 46770 | E20: 36316 | F20: Remaining days | H20: Remaining days | J20: WORKDAY(start,days) | K20: Returns the future date after a specified number of working days. | L20: Delivery planning
A21: 120 | B21: Rohit | C21: 44560 | D21: 46811 | E21: 35298 | F21: Year fraction | H21: Decimal year | J21: YEARFRAC(start,end) | K21: Returns the fraction of a year between two dates. | L21: Interest calculations
E24: Date Function
E25: =DATE(2025,10,6) -> 45936
I26: 30
C27: Day | D27: Month | E27: Year | F27: Date | G27: Due Date | H27: Difference | I27: Day | J27: month | K27: Year
C28: 15 | D28: 10 | E28: 2024 | F28: =DATE(E28,D28,C28) -> 45580 | G28: =F28+$I$26 -> 45610 | H28: =(TODAY()-F28)/365 -> 1.9643836 | I28: =TEXT(F28,"dddd") -> Tuesday | J28: =TEXT(D28,"mm") -> 01 | K28: =TEXT(F28,"yy") -> 24
C29: 6 | D29: 10 | E29: 2023 | F29: =DATE(E29,D29,C29) -> 45205 | G29: =F29+I26 -> 45235 | H29: =(TODAY()-F29)/365 -> 2.9917808 | I29: =TEXT(F29,"dddd") -> Friday | J29: =TEXT(D29,"mm") -> 01 | K29: =TEXT(F29,"yy") -> 23
F32: Edate | G32: Eomonth | H32: Workday
F33: =EDATE(F28,240) -> 52885 | G33: =EOMONTH(C29,10) -> 335 | H33: =WORKDAY(TODAY(),7) -> 46308
G34: us month ki last date
B38: Person DOB | C38: Age(Completed Years) | D38: Age(Months) | E38: Age( Days)
B39: 33615 | C39: =DATEDIF(B39,TODAY(),"y") -> 34 | D39: =DATEDIF(B39,TODAY(),"YM") -> 8 | E39: =DATEDIF(B39,TODAY(),"YD") -> 264
B40: 37063 | C40: =DATEDIF(B40,TODAY(),"y") -> 25 | D40: =DATEDIF(B40,TODAY(),"YM") -> 3 | E40: =DATEDIF(B40,TODAY(),"YD") -> 103
B43: Project Start | C43: Project End | D43: Working Days | E43: Working Days | F43: Holidays
B44: 46164 | C44: 46341 | D44: =NETWORKDAYS(B44,C44,F44:F46) -> 123 | E44: =NETWORKDAYS.INTL(B44,C44,11,F44:F46) -> 149 | F44: 46185
F45: 46279
F46: 46297

Sheet Exercise-1
A1: Exercise 1: Employee Experience Report (HR)
A3: Dataset
A5: Emp ID | B5: Employee | C5: Joining Date | D5: Birth Date | E5: Age | F5: Experience | G5: Retirement Age(After 35 years)
A6: 101 | B6: Amit | C6: 44211 | D6: 35925 | E6: =DATEDIF('Exercise-1'!D6,TODAY(),"y") -> 28 | F6: =DATEDIF(C6,TODAY(),"y") -> 5 | G6: ='Exercise-3'!D6=TEXT(G6,"mmmm") -> 0
A7: 102 | B7: Neha | C7: 43889 | D7: 36482 | E7: =DATEDIF('Exercise-1'!D7,TODAY(),"y") -> 26 | F7: =DATEDIF(C7,TODAY(),"y") -> 6 | G7: =EDATE(A3, 35*12) -> #VALUE!
A8: 103 | B8: Rahul | C8: 43529 | D8: 35789 | E8: =DATEDIF('Exercise-1'!D8,TODAY(),"y") -> 28 | F8: =DATEDIF(C8,TODAY(),"y") -> 7 | G8: =EDATE(A4, 35*12) -> 12784
A9: 104 | B9: Priya | C9: 44668 | D9: 35103 | E9: =DATEDIF('Exercise-1'!D9,TODAY(),"y") -> 30 | F9: =DATEDIF(C9,TODAY(),"y") -> 4 | G9: =EDATE(A5, 35*12) -> #VALUE!
A10: 105 | B10: Karan | C10: 43280 | D10: 34925 | E10: =DATEDIF('Exercise-1'!D10,TODAY(),"y") -> 31 | F10: =DATEDIF(C10,TODAY(),"y") -> 8 | G10: =EDATE(A6, 35*12) -> 12884
A12: Tasks
A14: 1. Display today's date. | E14: =TODAY() -> 46297
A15: 2. Calculate employee age in years.
A16: 3. Calculate years of experience.
A17: 4. Display birth month.
A18: 5. Display joining day name.
A19: 6. Find retirement date (Joining Date + 35 years).
A20: 7. Find retirement month.

Sheet Exercise-2
A1: Exercise 2: Courier Delivery Tracker
A3: Dataset
A5: Order ID | B5: Order Date | C5: Delivery Date | D5: Total Delivery Days | E5: Working Days | F5: last day of delivery month | G5: Weekday of Delivery
A6: O101 | B6: 46218 | C6: 46224 | D6: =C6-B6 -> 6 | E6: =NETWORKDAYS(B6,C6) -> 5 | F6: =EOMONTH(C6,0) -> 46234 | G6: =TEXT(C6,"dddd") -> Tuesday
A7: O102 | B7: 46219 | C7: 46227 | D7: =C7-B7 -> 8 | E7: =NETWORKDAYS(B7,C7) -> 7 | F7: =EOMONTH(C7,0) -> 46234 | G7: =TEXT(C7,"dddd") -> Friday
A8: O103 | B8: 46221 | C8: 46231 | D8: =C8-B8 -> 10 | E8: =NETWORKDAYS(B8,C8) -> 7 | F8: =EOMONTH(C8,0) -> 46234 | G8: =TEXT(C8,"dddd") -> Tuesday
A9: O104 | B9: 46223 | C9: 46228 | D9: =C9-B9 -> 5 | E9: =NETWORKDAYS(B9,C9) -> 5 | F9: =EOMONTH(C9,0) -> 46234 | G9: =TEXT(C9,"dddd") -> Saturday
A10: O105 | B10: 46225 | C10: 46232 | D10: =C10-B10 -> 7 | E10: =NETWORKDAYS(B10,C10) -> 6 | F10: =EOMONTH(C10,0) -> 46234 | G10: =TEXT(C10,"dddd") -> Wednesday
A12: Tasks
A14: 1. Calculate total delivery days.
A15: 2. Calculate working days only.
A16: 3. Find last day of delivery month.
A17: 4. Display weekday of delivery.

Sheet Exercise-3
A1: Exercise 3: Student Age Calculator
A3: Dataset
A5: Student | B5: DOB | C5: Age | D5: Birth Month | E5: Birth Day | F5: Birth Weekday | G5: Next Birthday year
A6: Ravi | B6: 38064 | C6: =DATEDIF(B6,TODAY(),"y") -> 22 | D6: =TEXT(B6,"mm") -> 03 | E6: =TEXT(B6,"dd") -> 18 | F6: =TEXT(B6,"dddd") -> Thursday | G6: =YEAR(TODAY())+(DATE(YEAR(TODAY()),MONTH(B6),DAY(B6))<TODAY()) -> 2027
A7: Sneha | B7: 38362 | C7: =DATEDIF(B7,TODAY(),"y") -> 21 | D7: =TEXT(B7,"mm") -> 01 | E7: =TEXT(B7,"dd") -> 10 | F7: =TEXT(B7,"dddd") -> Monday | G7: =YEAR(TODAY())+(DATE(YEAR(TODAY()),MONTH(B7),DAY(B7))<TODAY()) -> 2027
A8: Mohit | B8: 37947 | C8: =DATEDIF(B8,TODAY(),"y") -> 22 | D8: =TEXT(B8,"mm") -> 11 | E8: =TEXT(B8,"dd") -> 22 | F8: =TEXT(B8,"dddd") -> Saturday | G8: =YEAR(TODAY())+(DATE(YEAR(TODAY()),MONTH(B8),DAY(B8))<TODAY()) -> 2026
A9: Aisha | B9: 38183 | C9: =DATEDIF(B9,TODAY(),"y") -> 22 | D9: =TEXT(B9,"mm") -> 07 | E9: =TEXT(B9,"dd") -> 15 | F9: =TEXT(B9,"dddd") -> Thursday | G9: =YEAR(TODAY())+(DATE(YEAR(TODAY()),MONTH(B9),DAY(B9))<TODAY()) -> 2027
A10: Priya | B10: 38845 | C10: =DATEDIF(B10,TODAY(),"y") -> 20 | D10: =TEXT(B10,"mm") -> 05 | E10: =TEXT(B10,"dd") -> 08 | F10: =TEXT(B10,"dddd") -> Monday | G10: =YEAR(TODAY())+(DATE(YEAR(TODAY()),MONTH(B10),DAY(B10))<TODAY()) -> 2027
A12: Tasks
A14: 1. Calculate current age.
A15: 2. Display birth month.
A16: 3. Display birth day.
A17: 4. Display birth weekday.
A18: 5. Find next birthday year.

Sheet Exercise-4
A1: Exercise 4: Project Deadline
A3: Dataset
A5: Project | B5: Start Date | C5: Duration (Working Days) | D5: Completion Date | E5: Completion month | F5: Completion year | G5: Last day of Completion month
A6: ERP | B6: 46218 | C6: 45 | D6: =WORKDAY(B6,+C6) -> 46281 | E6: =TEXT(D6,"mmmm") -> September | F6: =TEXT(D6,"yy") -> 26 | G6: =EOMONTH(D6,0) -> 46295
A7: Website | B7: 46223 | C7: 30 | D7: =WORKDAY(B7,+C7) -> 46265 | E7: =TEXT(D7,"mmmm") -> August | F7: =TEXT(B7,"yy") -> 26 | G7: =EOMONTH(B7,0) -> 46234
A8: CRM | B8: 46228 | C8: 60 | D8: =WORKDAY(B8,+C8) -> 46311 | E8: =TEXT(D8,"mmmm") -> October | F8: =TEXT(B8,"yy") -> 26 | G8: =EOMONTH(B8,0) -> 46234
A9: Mobile App | B9: 46231 | C9: 50 | D9: =WORKDAY(B9,+C9) -> 46301 | E9: =TEXT(D9,"mmmm") -> October | F9: =TEXT(B9,"yy") -> 26 | G9: =EOMONTH(B9,0) -> 46234
A10: Dashboard | B10: 46233 | C10: 25 | D10: =WORKDAY(B10,+C10) -> 46268 | E10: =TEXT(D10,"mmmm") -> September | F10: =TEXT(B10,"yy") -> 26 | G10: =EOMONTH(B10,0) -> 46234
A12: Tasks
A14: 1. Calculate expected completion date.
A15: 2. Find completion month.
A16: 3. Find completion year.
A17: 4. Find last day of completion month.

Sheet Exercise-5
A1: Exercise 5: Loan Maturity
A3: Dataset
A5: Customer | B5: Loan Date | C5: Loan Period (Months) | D5: Maturity Date | E5: Maturity Year | F5: Maturity Month | G5: Last day of maturity month
A6: Amit | B6: 45303 | C6: 24 | D6: =EDATE(B6,C6) -> 46034 | E6: =YEAR(D6) -> 2026 | F6: =TEXT(D6,"mmmm") -> January | G6: =EOMONTH(D6,0) -> 46053
A7: Rahul | B7: 45003 | C7: 36 | D7: =EDATE(B7,C7) -> 46099 | E7: =YEAR(D7) -> 2026 | F7: =TEXT(D7,"mmmm") -> March | G7: =EOMONTH(D7,0) -> 46112
A8: Neha | B8: 45833 | C8: 18 | D8: =EDATE(B8,C8) -> 46381 | E8: =YEAR(D8) -> 2026 | F8: =TEXT(D8,"mmmm") -> December | G8: =EOMONTH(D8,0) -> 46387
A9: Priya | B9: 44600 | C9: 48 | D9: =EDATE(B9,C9) -> 46061 | E9: =YEAR(D9) -> 2026 | F9: =TEXT(D9,"mmmm") -> February | G9: =EOMONTH(D9,0) -> 46081
A10: Mohit | B10: 45610 | C10: 12 | D10: =EDATE(B10,C10) -> 45975 | E10: =YEAR(D10) -> 2025 | F10: =TEXT(D10,"mmmm") -> November | G10: =EOMONTH(D10,0) -> 45991
A12: Tasks
A14: 1. Calculate maturity date.
A15: 2. Find maturity year.
A16: 3. Find maturity month.
A17: 4. Find last day of maturity month.

Sheet Exercise-6
A1: Exercise 6: Invoice Due Date
A3: Dataset
A5: Invoice | B5: Invoice Date | C5: Credit Days | D5: Due Date | E5: Due Day Name | F5: Due Month | G5: Last day of due month
A6: INV101 | B6: 46213 | C6: 15 | D6: =B6+C6 -> 46228 | E6: =TEXT(D6,"dddd") -> Saturday | F6: =TEXT(D6,"mmmm") -> July | G6: =EOMONTH(D6,0) -> 46234
A7: INV102 | B7: 46215 | C7: 30 | D7: =B7+C7 -> 46245 | E7: =TEXT(D7,"dddd") -> Tuesday | F7: =TEXT(D7,"mmmm") -> August | G7: =EOMONTH(D7,0) -> 46265
A8: INV103 | B8: 46218 | C8: 45 | D8: =B8+C8 -> 46263 | E8: =TEXT(D8,"dddd") -> Saturday | F8: =TEXT(D8,"mmmm") -> August | G8: =EOMONTH(D8,0) -> 46265
A9: INV104 | B9: 46223 | C9: 60 | D9: =B9+C9 -> 46283 | E9: =TEXT(D9,"dddd") -> Friday | F9: =TEXT(D9,"mmmm") -> September | G9: =EOMONTH(D9,0) -> 46295
A10: INV105 | B10: 46228 | C10: 90 | D10: =B10+C10 -> 46318 | E10: =TEXT(D10,"dddd") -> Friday | F10: =TEXT(D10,"mmmm") -> October | G10: =EOMONTH(D10,0) -> 46326
A12: Tasks
A14: 1. Calculate due date.
A15: 2. Display due day name.
A16: 3. Display due month.
A17: 4. Find last day of due month.

Sheet Exercise 7
A1: Exercise 7: Event Planner
A3: Dataset
A5: Event | B5: Event Date | C5: Weekday | D5: Month Name | E5: Week Number | F5: Days remaining until the event | G5: last day of the event month
A6: Seminar | B6: 46249 | C6: =WEEKDAY(B6,2) -> 6 | D6: =TEXT(B6,"mmmm") -> August | E6: =WEEKNUM(B6) -> 33 | F6: =B6-TODAY() -> -48 | G6: =EOMONTH(B6,0) -> 46265
A7: Workshop | B7: 46262 | C7: =WEEKDAY(B7,2) -> 5 | D7: =TEXT(B7,"mmmm") -> August | E7: =WEEKNUM(B7) -> 35 | F7: =B7-TODAY() -> -35 | G7: =EOMONTH(B7,0) -> 46265
A8: Sports Day | B8: 46277 | C8: =WEEKDAY(B8,2) -> 6 | D8: =TEXT(B8,"mmmm") -> September | E8: =WEEKNUM(B8) -> 37 | F8: =B8-TODAY() -> -20 | G8: =EOMONTH(B8,0) -> 46295
A9: Hackathon | B9: 46320 | C9: =WEEKDAY(B9,2) -> 7 | D9: =TEXT(B9,"mmmm") -> October | E9: =WEEKNUM(B9) -> 44 | F9: =B9-TODAY() -> 23 | G9: =EOMONTH(B9,0) -> 46326
A10: Annual Day | B10: 46344 | C10: =WEEKDAY(B10,2) -> 3 | D10: =TEXT(B10,"mmmm") -> November | E10: =WEEKNUM(B10) -> 47 | F10: =B10-TODAY() -> 47 | G10: =EOMONTH(B10,0) -> 46356
A12: Tasks
A14: 1. Display weekday.
A15: 2. Display month name.
A16: 3. Display week number.
A17: 4. Find days remaining until the event.
A18: 5. Find last day of the event month.

Sheet Exercise-8
A1: Exercise 8: Comprehensive Date Functions Challenge
A3: Dataset
A5: Employee | B5: Joining Date | C5: DOB | D5: Project Start | E5: Project End | F5: Current Age | G5: Years of Experience | H5: Joining Weekday | I5: Joining month name | J5: Project duration in days | K5: Project working days | L5: Project completion month | M5: last day pf project completion month | N5: 3 Months to the joining date | O5: 1 yeat the project lasted
A6: Amit | B6: 43845 | C6: 35925 | D6: 46213 | E6: 46280 | F6: =DATEDIF(C6,TODAY(),"y") -> 28 | G6: =DATEDIF(B6,TODAY(),"y") -> 6 | H6: =TEXT(B6,"dddd") -> Wednesday | I6: =TEXT(B6,"mmmm") -> January | J6: =D6-E6 -> -67 | K6: =NETWORKDAYS(D6,E6) -> 48 | L6: =TEXT(E6,"mmmm") -> September | M6: =EOMONTH(E6,0) -> 46295 | N6: =EDATE(B6,3) -> 43936 | O6: =YEARFRAC(D6,E6) -> 0.18055556
A7: Neha | B7: 44273 | C7: 36482 | D7: 46218 | E7: 46323 | F7: =DATEDIF(C7,TODAY(),"y") -> 26 | G7: =DATEDIF(B7,TODAY(),"y") -> 5 | H7: =TEXT(B7,"dddd") -> Thursday | I7: =TEXT(B7,"mmmm") -> March | J7: =D7-E7 -> -105 | K7: =NETWORKDAYS(D7,E7) -> 76 | L7: =TEXT(E7,"mmmm") -> October | M7: =EOMONTH(E7,0) -> 46326 | N7: =EDATE(B7,3) -> 44365 | O7: =YEARFRAC(D7,E7) -> 0.28611111
A8: Rahul | B8: 43641 | C8: 35789 | D8: 46223 | E8: 46368 | F8: =DATEDIF(C8,TODAY(),"y") -> 28 | G8: =DATEDIF(B8,TODAY(),"y") -> 7 | H8: =TEXT(B8,"dddd") -> Tuesday | I8: =TEXT(B8,"mmmm") -> June | J8: =D8-E8 -> -145 | K8: =NETWORKDAYS(D8,E8) -> 105 | L8: =TEXT(E8,"mmmm") -> December | M8: =EOMONTH(E8,0) -> 46387 | N8: =EDATE(B8,3) -> 43733 | O8: =YEARFRAC(D8,E8) -> 0.39444444
A9: Priya | B9: 44604 | C9: 35103 | D9: 46228 | E9: 46344 | F9: =DATEDIF(C9,TODAY(),"y") -> 30 | G9: =DATEDIF(B9,TODAY(),"y") -> 4 | H9: =TEXT(B9,"dddd") -> Saturday | I9: =TEXT(B9,"mmmm") -> February | J9: =D9-E9 -> -116 | K9: =NETWORKDAYS(D9,E9) -> 83 | L9: =TEXT(E9,"mmmm") -> November | M9: =EOMONTH(E9,0) -> 46356 | N9: =EDATE(B9,3) -> 44693 | O9: =YEARFRAC(D9,E9) -> 0.31388889
A10: Karan | B10: 43320 | C10: 34925 | D10: 46233 | E10: 46409 | F10: =DATEDIF(C10,TODAY(),"y") -> 31 | G10: =DATEDIF(B10,TODAY(),"y") -> 8 | H10: =TEXT(B10,"dddd") -> Wednesday | I10: =TEXT(B10,"mmmm") -> August | J10: =D10-E10 -> -176 | K10: =NETWORKDAYS(D10,E10) -> 127 | L10: =TEXT(E10,"mmmm") -> January | M10: =EOMONTH(E10,0) -> 46418 | N10: =EDATE(B10,3) -> 43412 | O10: =YEARFRAC(D10,E10) -> 0.47777778
A12: Tasks
A14: 1. Calculate current age.
A15: 2. Calculate years of experience.
A16: 3. Find joining weekday.
A17: 4. Display joining month name.
A18: 5. Calculate project duration in days.
A19: 6. Calculate project working days.
A20: 7. Find project completion month.
A21: 8. Find last day of project completion month.
A22: 9. Find the date after adding 3 months to the joining date.
A23: 10. Calculate the fraction of a year the project lasted.
